[{"type":"TATE","from":"Tate Modern museum","artiste":"Joseph Mallord William Turner","artisteBio":"","date":"1827","title":"Group of Seated Figures","subTitle":"","medium":"Gouache and pen and ink on paper","dimensions":"support: 140 x 193 mm","medias":{"mini":"http://www.tate.org.uk/art/images/work/D/D20/D20852_8.jpg","medium":"http://www.tate.org.uk/art/images/work/D/D20/D20852_9.jpg","max":"http://www.tate.org.uk/art/images/work/D/D20/D20852_10.jpg","page":"http://www.tate.org.uk/art/artworks/turner-group-of-seated-figures-d20852"},"classification":"on paper, unique","credits":"Accepted by the nation as part of the Turner Bequest 1856"},{"type":"TATE","from":"Tate Modern museum","artiste":"Joseph Mallord William Turner","artisteBio":"","date":"1827","title":"The Medina and Castle","subTitle":"","medium":"Chalk, pen and ink and graphite on paper","dimensions":"support: 142 x 191 mm","medias":{"mini":"http://www.tate.org.uk/art/images/work/D/D20/D20853_8.jpg","medium":"http://www.tate.org.uk/art/images/work/D/D20/D20853_9.jpg","max":"http://www.tate.org.uk/art/images/work/D/D20/D20853_10.jpg","page":"http://www.tate.org.uk/art/artworks/turner-the-medina-and-castle-d20853"},"classification":"on paper, unique","credits":"Accepted by the nation as part of the Turner Bequest 1856"},{"type":"TATE","from":"Tate Modern museum","artiste":"Joseph Mallord William Turner","artisteBio":"","date":"1827","title":"Mouth of River. (?Medina)","subTitle":"","medium":"Chalk, pen and ink and graphite on paper","dimensions":"support: 142 x 194 mm","medias":{"mini":"http://www.tate.org.uk/art/images/work/D/D20/D20854_8.jpg","medium":"http://www.tate.org.uk/art/images/work/D/D20/D20854_9.jpg","max":"http://www.tate.org.uk/art/images/work/D/D20/D20854_10.jpg","page":"http://www.tate.org.uk/art/artworks/turner-mouth-of-river-medina-d20854"},"classification":"on paper, unique","credits":"Accepted by the nation as part of the Turner Bequest 1856"},{"type":"TATE","from":"Tate Modern museum","artiste":"Joseph Mallord William Turner","artisteBio":"","date":"1827","title":"A Port","subTitle":"","medium":"Pen and ink on paper","dimensions":"support: 137 x 193 mm","medias":{"mini":"http://www.tate.org.uk/art/images/work/D/D20/D20855_8.jpg","medium":"http://www.tate.org.uk/art/images/work/D/D20/D20855_9.jpg","max":"http://www.tate.org.uk/art/images/work/D/D20/D20855_10.jpg","page":"http://www.tate.org.uk/art/artworks/turner-a-port-d20855"},"classification":"on paper, unique","credits":"Accepted by the nation as part of the Turner Bequest 1856"},{"type":"TATE","from":"Tate Modern museum","artiste":"Joseph Mallord William Turner","artisteBio":"","date":"1827","title":"River, with Shipping, Seen through Trees","subTitle":"","medium":"Chalk and pen and ink on paper","dimensions":"support: 140 x 193 mm","medias":{"mini":"http://www.tate.org.uk/art/images/work/D/D20/D20856_8.jpg","medium":"http://www.tate.org.uk/art/images/work/D/D20/D20856_9.jpg","max":"http://www.tate.org.uk/art/images/work/D/D20/D20856_10.jpg","page":"http://www.tate.org.uk/art/artworks/turner-river-with-shipping-seen-through-trees-d20856"},"classification":"on paper, unique","credits":"Accepted by the nation as part of the Turner Bequest 1856"},{"type":"TATE","from":"Tate Modern museum","artiste":"Joseph Mallord William Turner","artisteBio":"","date":"1827","title":"Trees, with River in Mid Distance","subTitle":"","medium":"Chalk and pen and ink on paper","dimensions":"support: 138 x 192 mm","medias":{"mini":"http://www.tate.org.uk/art/images/work/D/D20/D20857_8.jpg","medium":"http://www.tate.org.uk/art/images/work/D/D20/D20857_9.jpg","max":"http://www.tate.org.uk/art/images/work/D/D20/D20857_10.jpg","page":"http://www.tate.org.uk/art/artworks/turner-trees-with-river-in-mid-distance-d20857"},"classification":"on paper, unique","credits":"Accepted by the nation as part of the Turner Bequest 1856"},{"type":"TATE","from":"Tate Modern museum","artiste":"Joseph Mallord William Turner","artisteBio":"","date":"1827","title":"Cowes Harbour, from East Cowes","subTitle":"","medium":"Chalk, pen and ink and graphite on paper","dimensions":"support: 140 x 191 mm","medias":{"mini":"http://www.tate.org.uk/art/images/work/D/D20/D20858_8.jpg","medium":"http://www.tate.org.uk/art/images/work/D/D20/D20858_9.jpg","max":"http://www.tate.org.uk/art/images/work/D/D20/D20858_10.jpg","page":"http://www.tate.org.uk/art/artworks/turner-cowes-harbour-from-east-cowes-d20858"},"classification":"on paper, unique","credits":"Accepted by the nation as part of the Turner Bequest 1856"},{"type":"TATE","from":"Tate Modern museum","artiste":"Joseph Mallord William Turner","artisteBio":"","date":"1827","title":"Trees, with Distant River and Shipping","subTitle":"","medium":"Chalk and pen and ink on paper","dimensions":"support: 136 x 193 mm","medias":{"mini":"http://www.tate.org.uk/art/images/work/D/D20/D20859_8.jpg","medium":"http://www.tate.org.uk/art/images/work/D/D20/D20859_9.jpg","max":"http://www.tate.org.uk/art/images/work/D/D20/D20859_10.jpg","page":"http://www.tate.org.uk/art/artworks/turner-trees-with-distant-river-and-shipping-d20859"},"classification":"on paper, unique","credits":"Accepted by the nation as part of the Turner Bequest 1856"},{"type":"TATE","from":"Tate Modern museum","artiste":"Joseph Mallord William Turner","artisteBio":"","date":"1827","title":"Trees, with Shipping Beyond","subTitle":"","medium":"Gouache, pen and ink and graphite on paper","dimensions":"support: 140 x 191 mm","medias":{"mini":"http://www.tate.org.uk/art/images/work/D/D20/D20860_8.jpg","medium":"http://www.tate.org.uk/art/images/work/D/D20/D20860_9.jpg","max":"http://www.tate.org.uk/art/images/work/D/D20/D20860_10.jpg","page":"http://www.tate.org.uk/art/artworks/turner-trees-with-shipping-beyond-d20860"},"classification":"on paper, unique","credits":"Accepted by the nation as part of the Turner Bequest 1856"},{"type":"TATE","from":"Tate Modern museum","artiste":"Joseph Mallord William Turner","artisteBio":"","date":"c.1827","title":"Sailing Vessel(s)","subTitle":"","medium":"Gouache and graphite on paper","dimensions":"support: 142 x 193 mm","medias":{"mini":"http://www.tate.org.uk/art/images/work/D/D20/D20861_8.jpg","medium":"http://www.tate.org.uk/art/images/work/D/D20/D20861_9.jpg","max":"http://www.tate.org.uk/art/images/work/D/D20/D20861_10.jpg","page":"http://www.tate.org.uk/art/artworks/turner-sailing-vessels-d20861"},"classification":"on paper, unique","credits":"Accepted by the nation as part of the Turner Bequest 1856"},{"type":"TATE","from":"Tate Modern museum","artiste":"Joseph Mallord William Turner","artisteBio":"","date":"c.1827","title":"Sailing Vessel(s)","subTitle":"","medium":"Gouache and graphite on paper","dimensions":"support: 138 x 195 mm","medias":{"mini":"http://www.tate.org.uk/art/images/work/D/D20/D20862_8.jpg","medium":"http://www.tate.org.uk/art/images/work/D/D20/D20862_9.jpg","max":"http://www.tate.org.uk/art/images/work/D/D20/D20862_10.jpg","page":"http://www.tate.org.uk/art/artworks/turner-sailing-vessels-d20862"},"classification":"on paper, unique","credits":"Accepted by the nation as part of the Turner Bequest 1856"},{"type":"TATE","from":"Tate Modern museum","artiste":"Joseph Mallord William Turner","artisteBio":"","date":"c.1827","title":"Sailing Vessel(s)","subTitle":"","medium":"Graphite on paper","dimensions":"support: 149 x 195 mm","medias":{"mini":"http://www.tate.org.uk/art/images/work/D/D20/D20863_8.jpg","medium":"http://www.tate.org.uk/art/images/work/D/D20/D20863_9.jpg","max":"http://www.tate.org.uk/art/images/work/D/D20/D20863_10.jpg","page":"http://www.tate.org.uk/art/artworks/turner-sailing-vessels-d20863"},"classification":"on paper, unique","credits":"Accepted by the nation as part of the Turner Bequest 1856"},{"type":"TATE","from":"Tate Modern museum","artiste":"Joseph Mallord William Turner","artisteBio":"","date":"c.1827","title":"Sailing Vessel(s)","subTitle":"","medium":"Graphite on paper","dimensions":"support: 142 x 191 mm","medias":{"mini":"http://www.tate.org.uk/art/images/work/D/D20/D20864_8.jpg","medium":"http://www.tate.org.uk/art/images/work/D/D20/D20864_9.jpg","max":"http://www.tate.org.uk/art/images/work/D/D20/D20864_10.jpg","page":"http://www.tate.org.uk/art/artworks/turner-sailing-vessels-d20864"},"classification":"on paper, unique","credits":"Accepted by the nation as part of the Turner Bequest 1856"},{"type":"TATE","from":"Tate Modern museum","artiste":"Joseph Mallord William Turner","artisteBio":"","date":"c.1827","title":"Sailing Vessel(s)","subTitle":"","medium":"Graphite on paper","dimensions":"support: 141 x 191 mm","medias":{"mini":"http://www.tate.org.uk/art/images/work/D/D20/D20865_8.jpg","medium":"http://www.tate.org.uk/art/images/work/D/D20/D20865_9.jpg","max":"http://www.tate.org.uk/art/images/work/D/D20/D20865_10.jpg","page":"http://www.tate.org.uk/art/artworks/turner-sailing-vessels-d20865"},"classification":"on paper, unique","credits":"Accepted by the nation as part of the Turner Bequest 1856"},{"type":"TATE","from":"Tate Modern museum","artiste":"Joseph Mallord William Turner","artisteBio":"","date":"c.1827","title":"Sailing Vessel(s)","subTitle":"","medium":"Gouache and graphite on paper","dimensions":"support: 138 x 191 mm","medias":{"mini":"http://www.tate.org.uk/art/images/work/D/D20/D20866_8.jpg","medium":"http://www.tate.org.uk/art/images/work/D/D20/D20866_9.jpg","max":"http://www.tate.org.uk/art/images/work/D/D20/D20866_10.jpg","page":"http://www.tate.org.uk/art/artworks/turner-sailing-vessels-d20866"},"classification":"on paper, unique","credits":"Accepted by the nation as part of the Turner Bequest 1856"},{"type":"TATE","from":"Tate Modern museum","artiste":"Joseph Mallord William Turner","artisteBio":"","date":"c.1827","title":"Sailing Vessel(s)","subTitle":"","medium":"Gouache and graphite on paper","dimensions":"support: 137 x 197 mm","medias":{"mini":"http://www.tate.org.uk/art/images/work/D/D20/D20867_8.jpg","medium":"http://www.tate.org.uk/art/images/work/D/D20/D20867_9.jpg","max":"http://www.tate.org.uk/art/images/work/D/D20/D20867_10.jpg","page":"http://www.tate.org.uk/art/artworks/turner-sailing-vessels-d20867"},"classification":"on paper, unique","credits":"Accepted by the nation as part of the Turner Bequest 1856"},{"type":"TATE","from":"Tate Modern museum","artiste":"Joseph Mallord William Turner","artisteBio":"","date":"c.1827","title":"Sailing Vessel(s)","subTitle":"","medium":"Graphite on paper","dimensions":"support: 144 x 191 mm","medias":{"mini":"http://www.tate.org.uk/art/images/work/D/D20/D20868_8.jpg","medium":"http://www.tate.org.uk/art/images/work/D/D20/D20868_9.jpg","max":"http://www.tate.org.uk/art/images/work/D/D20/D20868_10.jpg","page":"http://www.tate.org.uk/art/artworks/turner-sailing-vessels-d20868"},"classification":"on paper, unique","credits":"Accepted by the nation as part of the Turner Bequest 1856"},{"type":"TATE","from":"Tate Modern museum","artiste":"Joseph Mallord William Turner","artisteBio":"","date":"c.1827","title":"Sailing Vessel(s)","subTitle":"","medium":"Graphite on paper","dimensions":"support: 140 x 196 mm","medias":{"mini":"http://www.tate.org.uk/art/images/work/D/D20/D20869_8.jpg","medium":"http://www.tate.org.uk/art/images/work/D/D20/D20869_9.jpg","max":"http://www.tate.org.uk/art/images/work/D/D20/D20869_10.jpg","page":"http://www.tate.org.uk/art/artworks/turner-sailing-vessels-d20869"},"classification":"on paper, unique","credits":"Accepted by the nation as part of the Turner Bequest 1856"},{"type":"TATE","from":"Tate Modern museum","artiste":"Joseph Mallord William Turner","artisteBio":"","date":"c.1827","title":"Sailing Vessel(s)","subTitle":"","medium":"Graphite on paper","dimensions":"support: 143 x 199 mm","medias":{"mini":"http://www.tate.org.uk/art/images/work/D/D20/D20870_8.jpg","medium":"http://www.tate.org.uk/art/images/work/D/D20/D20870_9.jpg","max":"http://www.tate.org.uk/art/images/work/D/D20/D20870_10.jpg","page":"http://www.tate.org.uk/art/artworks/turner-sailing-vessels-d20870"},"classification":"on paper, unique","credits":"Accepted by the nation as part of the Turner Bequest 1856"},{"type":"TATE","from":"Tate Modern museum","artiste":"Joseph Mallord William Turner","artisteBio":"","date":"c.1827","title":"Sailing Vessel(s)","subTitle":"","medium":"Graphite on paper","dimensions":"support: 140 x 199 mm","medias":{"mini":"http://www.tate.org.uk/art/images/work/D/D20/D20871_8.jpg","medium":"http://www.tate.org.uk/art/images/work/D/D20/D20871_9.jpg","max":"http://www.tate.org.uk/art/images/work/D/D20/D20871_10.jpg","page":"http://www.tate.org.uk/art/artworks/turner-sailing-vessels-d20871"},"classification":"on paper, unique","credits":"Accepted by the nation as part of the Turner Bequest 1856"},{"type":"TATE","from":"Tate Modern museum","artiste":"Joseph Mallord William Turner","artisteBio":"","date":"c.1827","title":"Sailing Vessel(s)","subTitle":"","medium":"Graphite on paper","dimensions":"support: 148 x 192 mm","medias":{"mini":"http://www.tate.org.uk/art/images/work/D/D20/D20872_8.jpg","medium":"http://www.tate.org.uk/art/images/work/D/D20/D20872_9.jpg","max":"http://www.tate.org.uk/art/images/work/D/D20/D20872_10.jpg","page":"http://www.tate.org.uk/art/artworks/turner-sailing-vessels-d20872"},"classification":"on paper, unique","credits":"Accepted by the nation as part of the Turner Bequest 1856"},{"type":"TATE","from":"Tate Modern museum","artiste":"Joseph Mallord William Turner","artisteBio":"","date":"c.1827","title":"Sailing Vessel(s)","subTitle":"","medium":"Gouache and graphite on paper","dimensions":"support: 144 x 183 mm","medias":{"mini":"http://www.tate.org.uk/art/images/work/D/D20/D20873_8.jpg","medium":"http://www.tate.org.uk/art/images/work/D/D20/D20873_9.jpg","max":"http://www.tate.org.uk/art/images/work/D/D20/D20873_10.jpg","page":"http://www.tate.org.uk/art/artworks/turner-sailing-vessels-d20873"},"classification":"on paper, unique","credits":"Accepted by the nation as part of the Turner Bequest 1856"},{"type":"TATE","from":"Tate Modern museum","artiste":"Joseph Mallord William Turner","artisteBio":"","date":"c.1827","title":"Sailing Vessel(s)","subTitle":"","medium":"Gouache and graphite on paper","dimensions":"support: 142 x 193 mm","medias":{"mini":"http://www.tate.org.uk/art/images/work/D/D20/D20874_8.jpg","medium":"http://www.tate.org.uk/art/images/work/D/D20/D20874_9.jpg","max":"http://www.tate.org.uk/art/images/work/D/D20/D20874_10.jpg","page":"http://www.tate.org.uk/art/artworks/turner-sailing-vessels-d20874"},"classification":"on paper, unique","credits":"Accepted by the nation as part of the Turner Bequest 1856"},{"type":"TATE","from":"Tate Modern museum","artiste":"Joseph Mallord William Turner","artisteBio":"","date":"c.1827","title":"Sailing Vessel(s)","subTitle":"","medium":"Gouache and graphite on paper","dimensions":"support: 141 x 195 mm","medias":{"mini":"http://www.tate.org.uk/art/images/work/D/D20/D20875_8.jpg","medium":"http://www.tate.org.uk/art/images/work/D/D20/D20875_9.jpg","max":"http://www.tate.org.uk/art/images/work/D/D20/D20875_10.jpg","page":"http://www.tate.org.uk/art/artworks/turner-sailing-vessels-d20875"},"classification":"on paper, unique","credits":"Accepted by the nation as part of the Turner Bequest 1856"},{"type":"TATE","from":"Tate Modern museum","artiste":"Joseph Mallord William Turner","artisteBio":"","date":"c.1827","title":"Sailing Vessel(s)","subTitle":"","medium":"Graphite on paper","dimensions":"support: 136 x 191 mm","medias":{"mini":"http://www.tate.org.uk/art/images/work/D/D20/D20876_8.jpg","medium":"http://www.tate.org.uk/art/images/work/D/D20/D20876_9.jpg","max":"http://www.tate.org.uk/art/images/work/D/D20/D20876_10.jpg","page":"http://www.tate.org.uk/art/artworks/turner-sailing-vessels-d20876"},"classification":"on paper, unique","credits":"Accepted by the nation as part of the Turner Bequest 1856"},{"type":"TATE","from":"Tate Modern museum","artiste":"Joseph Mallord William Turner","artisteBio":"","date":"c.1827","title":"Sailing Vessel(s)","subTitle":"","medium":"Graphite on paper","dimensions":"support: 141 x 189 mm","medias":{"mini":"http://www.tate.org.uk/art/images/work/D/D20/D20877_8.jpg","medium":"http://www.tate.org.uk/art/images/work/D/D20/D20877_9.jpg","max":"http://www.tate.org.uk/art/images/work/D/D20/D20877_10.jpg","page":"http://www.tate.org.uk/art/artworks/turner-sailing-vessels-d20877"},"classification":"on paper, unique","credits":"Accepted by the nation as part of the Turner Bequest 1856"},{"type":"TATE","from":"Tate Modern museum","artiste":"Joseph Mallord William Turner","artisteBio":"","date":"c.1827","title":"Sailing Vessel(s)","subTitle":"","medium":"Graphite on paper","dimensions":"support: 138 x 193 mm","medias":{"mini":"http://www.tate.org.uk/art/images/work/D/D20/D20878_8.jpg","medium":"http://www.tate.org.uk/art/images/work/D/D20/D20878_9.jpg","max":"http://www.tate.org.uk/art/images/work/D/D20/D20878_10.jpg","page":"http://www.tate.org.uk/art/artworks/turner-sailing-vessels-d20878"},"classification":"on paper, unique","credits":"Accepted by the nation as part of the Turner Bequest 1856"},{"type":"TATE","from":"Tate Modern museum","artiste":"Joseph Mallord William Turner","artisteBio":"","date":"c.1827","title":"Sailing Vessel(s)","subTitle":"","medium":"Graphite on paper","dimensions":"support: 140 x 190 mm","medias":{"mini":"http://www.tate.org.uk/art/images/work/D/D20/D20879_8.jpg","medium":"http://www.tate.org.uk/art/images/work/D/D20/D20879_9.jpg","max":"http://www.tate.org.uk/art/images/work/D/D20/D20879_10.jpg","page":"http://www.tate.org.uk/art/artworks/turner-sailing-vessels-d20879"},"classification":"on paper, unique","credits":"Accepted by the nation as part of the Turner Bequest 1856"},{"type":"TATE","from":"Tate Modern museum","artiste":"Joseph Mallord William Turner","artisteBio":"","date":"c.1827","title":"Sailing Vessel(s)","subTitle":"","medium":"Graphite on paper","dimensions":"support: 134 x 190 mm","medias":{"mini":"http://www.tate.org.uk/art/images/work/D/D20/D20880_8.jpg","medium":"http://www.tate.org.uk/art/images/work/D/D20/D20880_9.jpg","max":"http://www.tate.org.uk/art/images/work/D/D20/D20880_10.jpg","page":"http://www.tate.org.uk/art/artworks/turner-sailing-vessels-d20880"},"classification":"on paper, unique","credits":"Accepted by the nation as part of the Turner Bequest 1856"},{"type":"TATE","from":"Tate Modern museum","artiste":"Joseph Mallord William Turner","artisteBio":"","date":"c.1827","title":"Sailing Vessel(s)","subTitle":"","medium":"Graphite on paper","dimensions":"support: 135 x 196 mm","medias":{"mini":"http://www.tate.org.uk/art/images/work/D/D20/D20881_8.jpg","medium":"http://www.tate.org.uk/art/images/work/D/D20/D20881_9.jpg","max":"http://www.tate.org.uk/art/images/work/D/D20/D20881_10.jpg","page":"http://www.tate.org.uk/art/artworks/turner-sailing-vessels-d20881"},"classification":"on paper, unique","credits":"Accepted by the nation as part of the Turner Bequest 1856"},{"type":"TATE","from":"Tate Modern museum","artiste":"Joseph Mallord William Turner","artisteBio":"","date":"c.1827","title":"Sailing Vessel(s)","subTitle":"","medium":"Gouache and graphite on paper","dimensions":"support: 143 x 192 mm","medias":{"mini":"http://www.tate.org.uk/art/images/work/D/D20/D20882_8.jpg","medium":"http://www.tate.org.uk/art/images/work/D/D20/D20882_9.jpg","max":"http://www.tate.org.uk/art/images/work/D/D20/D20882_10.jpg","page":"http://www.tate.org.uk/art/artworks/turner-sailing-vessels-d20882"},"classification":"on paper, unique","credits":"Accepted by the nation as part of the Turner Bequest 1856"},{"type":"TATE","from":"Tate Modern museum","artiste":"Joseph Mallord William Turner","artisteBio":"","date":"c.1827","title":"Sailing Vessel(s)","subTitle":"","medium":"Gouache on paper","dimensions":"support: 138 x 190 mm","medias":{"mini":"http://www.tate.org.uk/art/images/work/D/D20/D20883_8.jpg","medium":"http://www.tate.org.uk/art/images/work/D/D20/D20883_9.jpg","max":"http://www.tate.org.uk/art/images/work/D/D20/D20883_10.jpg","page":"http://www.tate.org.uk/art/artworks/turner-sailing-vessels-d20883"},"classification":"on paper, unique","credits":"Accepted by the nation as part of the Turner Bequest 1856"},{"type":"TATE","from":"Tate Modern museum","artiste":"Joseph Mallord William Turner","artisteBio":"","date":"c.1827","title":"Sailing Vessel(s)","subTitle":"","medium":"Graphite on paper","dimensions":"support: 138 x 195 mm","medias":{"mini":"http://www.tate.org.uk/art/images/work/D/D20/D20884_8.jpg","medium":"http://www.tate.org.uk/art/images/work/D/D20/D20884_9.jpg","max":"http://www.tate.org.uk/art/images/work/D/D20/D20884_10.jpg","page":"http://www.tate.org.uk/art/artworks/turner-sailing-vessels-d20884"},"classification":"on paper, unique","credits":"Accepted by the nation as part of the Turner Bequest 1856"},{"type":"TATE","from":"Tate Modern museum","artiste":"Joseph Mallord William Turner","artisteBio":"","date":"c.1827","title":"Sailing Vessel(s)","subTitle":"","medium":"Gouache and graphite on paper","dimensions":"support: 142 x 191 mm","medias":{"mini":"http://www.tate.org.uk/art/images/work/D/D20/D20885_8.jpg","medium":"http://www.tate.org.uk/art/images/work/D/D20/D20885_9.jpg","max":"http://www.tate.org.uk/art/images/work/D/D20/D20885_10.jpg","page":"http://www.tate.org.uk/art/artworks/turner-sailing-vessels-d20885"},"classification":"on paper, unique","credits":"Accepted by the nation as part of the Turner Bequest 1856"},{"type":"TATE","from":"Tate Modern museum","artiste":"Joseph Mallord William Turner","artisteBio":"","date":"c.1827","title":"Sailing Vessel(s)","subTitle":"","medium":"Graphite on paper","dimensions":"support: 140 x 195 mm","medias":{"mini":"http://www.tate.org.uk/art/images/work/D/D20/D20886_8.jpg","medium":"http://www.tate.org.uk/art/images/work/D/D20/D20886_9.jpg","max":"http://www.tate.org.uk/art/images/work/D/D20/D20886_10.jpg","page":"http://www.tate.org.uk/art/artworks/turner-sailing-vessels-d20886"},"classification":"on paper, unique","credits":"Accepted by the nation as part of the Turner Bequest 1856"},{"type":"TATE","from":"Tate Modern museum","artiste":"Joseph Mallord William Turner","artisteBio":"","date":"c.1827","title":"Sailing Vessel(s)","subTitle":"","medium":"Graphite on paper","dimensions":"support: 140 x 191 mm","medias":{"mini":"http://www.tate.org.uk/art/images/work/D/D20/D20887_8.jpg","medium":"http://www.tate.org.uk/art/images/work/D/D20/D20887_9.jpg","max":"http://www.tate.org.uk/art/images/work/D/D20/D20887_10.jpg","page":"http://www.tate.org.uk/art/artworks/turner-sailing-vessels-d20887"},"classification":"on paper, unique","credits":"Accepted by the nation as part of the Turner Bequest 1856"},{"type":"TATE","from":"Tate Modern museum","artiste":"Joseph Mallord William Turner","artisteBio":"","date":"c.1827","title":"Sailing Vessel(s)","subTitle":"","medium":"Graphite on paper","dimensions":"support: 144 x 191 mm","medias":{"mini":"http://www.tate.org.uk/art/images/work/D/D20/D20888_8.jpg","medium":"http://www.tate.org.uk/art/images/work/D/D20/D20888_9.jpg","max":"http://www.tate.org.uk/art/images/work/D/D20/D20888_10.jpg","page":"http://www.tate.org.uk/art/artworks/turner-sailing-vessels-d20888"},"classification":"on paper, unique","credits":"Accepted by the nation as part of the Turner Bequest 1856"},{"type":"TATE","from":"Tate Modern museum","artiste":"Joseph Mallord William Turner","artisteBio":"","date":"c.1827","title":"Sailing Vessel(s)","subTitle":"","medium":"Graphite on paper","dimensions":"support: 143 x 191 mm","medias":{"mini":"http://www.tate.org.uk/art/images/work/D/D20/D20889_8.jpg","medium":"http://www.tate.org.uk/art/images/work/D/D20/D20889_9.jpg","max":"http://www.tate.org.uk/art/images/work/D/D20/D20889_10.jpg","page":"http://www.tate.org.uk/art/artworks/turner-sailing-vessels-d20889"},"classification":"on paper, unique","credits":"Accepted by the nation as part of the Turner Bequest 1856"},{"type":"TATE","from":"Tate Modern museum","artiste":"Joseph Mallord William Turner","artisteBio":"","date":"c.1827","title":"Sailing Vessel(s)","subTitle":"","medium":"Graphite on paper","dimensions":"support: 141 x 190 mm","medias":{"mini":"http://www.tate.org.uk/art/images/work/D/D20/D20890_8.jpg","medium":"http://www.tate.org.uk/art/images/work/D/D20/D20890_9.jpg","max":"http://www.tate.org.uk/art/images/work/D/D20/D20890_10.jpg","page":"http://www.tate.org.uk/art/artworks/turner-sailing-vessels-d20890"},"classification":"on paper, unique","credits":"Accepted by the nation as part of the Turner Bequest 1856"},{"type":"TATE","from":"Tate Modern museum","artiste":"Joseph Mallord William Turner","artisteBio":"","date":"c.1827","title":"Sailing Vessel(s)","subTitle":"","medium":"Gouache and graphite on paper","dimensions":"support: 139 x 192 mm","medias":{"mini":"http://www.tate.org.uk/art/images/work/D/D20/D20891_8.jpg","medium":"http://www.tate.org.uk/art/images/work/D/D20/D20891_9.jpg","max":"http://www.tate.org.uk/art/images/work/D/D20/D20891_10.jpg","page":"http://www.tate.org.uk/art/artworks/turner-sailing-vessels-d20891"},"classification":"on paper, unique","credits":"Accepted by the nation as part of the Turner Bequest 1856"},{"type":"TATE","from":"Tate Modern museum","artiste":"Joseph Mallord William Turner","artisteBio":"","date":"c.1827","title":"Sailing Vessel(s)","subTitle":"","medium":"Gouache and graphite on paper","dimensions":"support: 141 x 193 mm","medias":{"mini":"http://www.tate.org.uk/art/images/work/D/D20/D20892_8.jpg","medium":"http://www.tate.org.uk/art/images/work/D/D20/D20892_9.jpg","max":"http://www.tate.org.uk/art/images/work/D/D20/D20892_10.jpg","page":"http://www.tate.org.uk/art/artworks/turner-sailing-vessels-d20892"},"classification":"on paper, unique","credits":"Accepted by the nation as part of the Turner Bequest 1856"},{"type":"TATE","from":"Tate Modern museum","artiste":"Joseph Mallord William Turner","artisteBio":"","date":"c.1827","title":"Sailing Vessel(s)","subTitle":"","medium":"Gouache and graphite on paper","dimensions":"support: 145 x 193 mm","medias":{"mini":"http://www.tate.org.uk/art/images/work/D/D20/D20893_8.jpg","medium":"http://www.tate.org.uk/art/images/work/D/D20/D20893_9.jpg","max":"http://www.tate.org.uk/art/images/work/D/D20/D20893_10.jpg","page":"http://www.tate.org.uk/art/artworks/turner-sailing-vessels-d20893"},"classification":"on paper, unique","credits":"Accepted by the nation as part of the Turner Bequest 1856"},{"type":"TATE","from":"Tate Modern museum","artiste":"Joseph Mallord William Turner","artisteBio":"","date":"c.1827","title":"Sailing Vessel(s)","subTitle":"","medium":"Graphite on paper","dimensions":"support: 144 x 186 mm","medias":{"mini":"http://www.tate.org.uk/art/images/work/D/D20/D20894_8.jpg","medium":"http://www.tate.org.uk/art/images/work/D/D20/D20894_9.jpg","max":"http://www.tate.org.uk/art/images/work/D/D20/D20894_10.jpg","page":"http://www.tate.org.uk/art/artworks/turner-sailing-vessels-d20894"},"classification":"on paper, unique","credits":"Accepted by the nation as part of the Turner Bequest 1856"},{"type":"TATE","from":"Tate Modern museum","artiste":"Joseph Mallord William Turner","artisteBio":"","date":"c.1827","title":"Sailing Vessel(s)","subTitle":"","medium":"Graphite on paper","dimensions":"support: 144 x 192 mm","medias":{"mini":"http://www.tate.org.uk/art/images/work/D/D20/D20895_8.jpg","medium":"http://www.tate.org.uk/art/images/work/D/D20/D20895_9.jpg","max":"http://www.tate.org.uk/art/images/work/D/D20/D20895_10.jpg","page":"http://www.tate.org.uk/art/artworks/turner-sailing-vessels-d20895"},"classification":"on paper, unique","credits":"Accepted by the nation as part of the Turner Bequest 1856"},{"type":"TATE","from":"Tate Modern museum","artiste":"Joseph Mallord William Turner","artisteBio":"","date":"c.1827","title":"Sailing Vessel(s)","subTitle":"","medium":"Chalk and graphite on paper","dimensions":"support: 143 x 192 mm","medias":{"mini":"http://www.tate.org.uk/art/images/work/D/D20/D20896_8.jpg","medium":"http://www.tate.org.uk/art/images/work/D/D20/D20896_9.jpg","max":"http://www.tate.org.uk/art/images/work/D/D20/D20896_10.jpg","page":"http://www.tate.org.uk/art/artworks/turner-sailing-vessels-d20896"},"classification":"on paper, unique","credits":"Accepted by the nation as part of the Turner Bequest 1856"},{"type":"TATE","from":"Tate Modern museum","artiste":"Joseph Mallord William Turner","artisteBio":"","date":"c.1827","title":"Sailing Vessel(s)","subTitle":"","medium":"Chalk and graphite on paper","dimensions":"support: 142 x 193 mm","medias":{"mini":"http://www.tate.org.uk/art/images/work/D/D20/D20897_8.jpg","medium":"http://www.tate.org.uk/art/images/work/D/D20/D20897_9.jpg","max":"http://www.tate.org.uk/art/images/work/D/D20/D20897_10.jpg","page":"http://www.tate.org.uk/art/artworks/turner-sailing-vessels-d20897"},"classification":"on paper, unique","credits":"Accepted by the nation as part of the Turner Bequest 1856"},{"type":"TATE","from":"Tate Modern museum","artiste":"Joseph Mallord William Turner","artisteBio":"","date":"c.1827","title":"Sailing Vessel(s)","subTitle":"","medium":"Chalk and graphite on paper","dimensions":"support: 142 x 193 mm","medias":{"mini":"http://www.tate.org.uk/art/images/work/D/D20/D20898_8.jpg","medium":"http://www.tate.org.uk/art/images/work/D/D20/D20898_9.jpg","max":"http://www.tate.org.uk/art/images/work/D/D20/D20898_10.jpg","page":"http://www.tate.org.uk/art/artworks/turner-sailing-vessels-d20898"},"classification":"on paper, unique","credits":"Accepted by the nation as part of the Turner Bequest 1856"},{"type":"TATE","from":"Tate Modern museum","artiste":"Joseph Mallord William Turner","artisteBio":"","date":"c.1827","title":"Sailing Vessel(s)","subTitle":"","medium":"Gouache and graphite on paper","dimensions":"support: 140 x 192 mm","medias":{"mini":"http://www.tate.org.uk/art/images/work/D/D20/D20899_8.jpg","medium":"http://www.tate.org.uk/art/images/work/D/D20/D20899_9.jpg","max":"http://www.tate.org.uk/art/images/work/D/D20/D20899_10.jpg","page":"http://www.tate.org.uk/art/artworks/turner-sailing-vessels-d20899"},"classification":"on paper, unique","credits":"Accepted by the nation as part of the Turner Bequest 1856"},{"type":"TATE","from":"Tate Modern museum","artiste":"Joseph Mallord William Turner","artisteBio":"","date":"c.1827","title":"Sailing Vessel(s)","subTitle":"","medium":"Gouache and graphite on paper","dimensions":"support: 142 x 192 mm","medias":{"mini":"http://www.tate.org.uk/art/images/work/D/D20/D20900_8.jpg","medium":"http://www.tate.org.uk/art/images/work/D/D20/D20900_9.jpg","max":"http://www.tate.org.uk/art/images/work/D/D20/D20900_10.jpg","page":"http://www.tate.org.uk/art/artworks/turner-sailing-vessels-d20900"},"classification":"on paper, unique","credits":"Accepted by the nation as part of the Turner Bequest 1856"},{"type":"TATE","from":"Tate Modern museum","artiste":"Joseph Mallord William Turner","artisteBio":"","date":"c.1827","title":"Sailing Vessel(s)","subTitle":"","medium":"Gouache and graphite on paper","dimensions":"support: 141 x 192 mm","medias":{"mini":"http://www.tate.org.uk/art/images/work/D/D20/D20901_8.jpg","medium":"http://www.tate.org.uk/art/images/work/D/D20/D20901_9.jpg","max":"http://www.tate.org.uk/art/images/work/D/D20/D20901_10.jpg","page":"http://www.tate.org.uk/art/artworks/turner-sailing-vessels-d20901"},"classification":"on paper, unique","credits":"Accepted by the nation as part of the Turner Bequest 1856"},{"type":"TATE","from":"Tate Modern museum","artiste":"Joseph Mallord William Turner","artisteBio":"","date":"c.1827","title":"Sailing Vessel(s)","subTitle":"","medium":"Gouache and graphite on paper","dimensions":"support: 145 x 191 mm","medias":{"mini":"http://www.tate.org.uk/art/images/work/D/D20/D20902_8.jpg","medium":"http://www.tate.org.uk/art/images/work/D/D20/D20902_9.jpg","max":"http://www.tate.org.uk/art/images/work/D/D20/D20902_10.jpg","page":"http://www.tate.org.uk/art/artworks/turner-sailing-vessels-d20902"},"classification":"on paper, unique","credits":"Accepted by the nation as part of the Turner Bequest 1856"},{"type":"TATE","from":"Tate Modern museum","artiste":"Joseph Mallord William Turner","artisteBio":"","date":"c.1827","title":"Sailing Vessel(s)","subTitle":"","medium":"Gouache and graphite on paper","dimensions":"support: 144 x 189 mm","medias":{"mini":"http://www.tate.org.uk/art/images/work/D/D20/D20903_8.jpg","medium":"http://www.tate.org.uk/art/images/work/D/D20/D20903_9.jpg","max":"http://www.tate.org.uk/art/images/work/D/D20/D20903_10.jpg","page":"http://www.tate.org.uk/art/artworks/turner-sailing-vessels-d20903"},"classification":"on paper, unique","credits":"Accepted by the nation as part of the Turner Bequest 1856"},{"type":"TATE","from":"Tate Modern museum","artiste":"Joseph Mallord William Turner","artisteBio":"","date":"c.1827","title":"Sailing Vessel(s)","subTitle":"","medium":"Gouache and graphite on paper","dimensions":"support: 145 x 190 mm","medias":{"mini":"http://www.tate.org.uk/art/images/work/D/D20/D20904_8.jpg","medium":"http://www.tate.org.uk/art/images/work/D/D20/D20904_9.jpg","max":"http://www.tate.org.uk/art/images/work/D/D20/D20904_10.jpg","page":"http://www.tate.org.uk/art/artworks/turner-sailing-vessels-d20904"},"classification":"on paper, unique","credits":"Accepted by the nation as part of the Turner Bequest 1856"},{"type":"TATE","from":"Tate Modern museum","artiste":"Joseph Mallord William Turner","artisteBio":"","date":"1828","title":"Buildings","subTitle":"","medium":"Graphite on paper","dimensions":"support: 179 x 117 mm","medias":{"mini":"http://www.tate.org.uk/art/images/work/D/D20/D20905_8.jpg","medium":"http://www.tate.org.uk/art/images/work/D/D20/D20905_9.jpg","max":"http://www.tate.org.uk/art/images/work/D/D20/D20905_10.jpg","page":"http://www.tate.org.uk/art/artworks/turner-buildings-d20905"},"classification":"on paper, unique","credits":"Accepted by the nation as part of the Turner Bequest 1856"},{"type":"TATE","from":"Tate Modern museum","artiste":"Joseph Mallord William Turner","artisteBio":"","date":"1828","title":"Buildings","subTitle":"","medium":"Graphite on paper","dimensions":"support: 179 x 117 mm","medias":{"mini":"http://www.tate.org.uk/art/images/work/D/D20/D20906_8.jpg","medium":"http://www.tate.org.uk/art/images/work/D/D20/D20906_9.jpg","max":"http://www.tate.org.uk/art/images/work/D/D20/D20906_10.jpg","page":"http://www.tate.org.uk/art/artworks/turner-buildings-d20906"},"classification":"on paper, unique","credits":"Accepted by the nation as part of the Turner Bequest 1856"},{"type":"TATE","from":"Tate Modern museum","artiste":"Joseph Mallord William Turner","artisteBio":"","date":"1828","title":"Gothic Building","subTitle":"","medium":"Graphite on paper","dimensions":"support: 179 x 117 mm","medias":{"mini":"http://www.tate.org.uk/art/images/work/D/D20/D20907_8.jpg","medium":"http://www.tate.org.uk/art/images/work/D/D20/D20907_9.jpg","max":"http://www.tate.org.uk/art/images/work/D/D20/D20907_10.jpg","page":"http://www.tate.org.uk/art/artworks/turner-gothic-building-d20907"},"classification":"on paper, unique","credits":"Accepted by the nation as part of the Turner Bequest 1856"},{"type":"TATE","from":"Tate Modern museum","artiste":"Joseph Mallord William Turner","artisteBio":"","date":"1828","title":"Gien on the Loire","subTitle":"","medium":"Graphite on paper","dimensions":"support: 179 x 117 mm","medias":{"mini":"http://www.tate.org.uk/art/images/work/D/D20/D20908_8.jpg","medium":"http://www.tate.org.uk/art/images/work/D/D20/D20908_9.jpg","max":"http://www.tate.org.uk/art/images/work/D/D20/D20908_10.jpg","page":"http://www.tate.org.uk/art/artworks/turner-gien-on-the-loire-d20908"},"classification":"on paper, unique","credits":"Accepted by the nation as part of the Turner Bequest 1856"},{"type":"TATE","from":"Tate Modern museum","artiste":"Joseph Mallord William Turner","artisteBio":"","date":"1828","title":"Landscape, with Church and Other Buildings","subTitle":"","medium":"Graphite on paper","dimensions":"support: 179 x 117 mm","medias":{"mini":"http://www.tate.org.uk/art/images/work/D/D20/D20909_8.jpg","medium":"http://www.tate.org.uk/art/images/work/D/D20/D20909_9.jpg","max":"http://www.tate.org.uk/art/images/work/D/D20/D20909_10.jpg","page":"http://www.tate.org.uk/art/artworks/turner-landscape-with-church-and-other-buildings-d20909"},"classification":"on paper, unique","credits":"Accepted by the nation as part of the Turner Bequest 1856"},{"type":"TATE","from":"Tate Modern museum","artiste":"Joseph Mallord William Turner","artisteBio":"","date":"1828","title":"Landscape, ?Gomidon [Turner]","subTitle":"","medium":"Graphite on paper","dimensions":"support: 179 x 117 mm","medias":{"mini":"http://www.tate.org.uk/art/images/work/D/D20/D20910_8.jpg","medium":"http://www.tate.org.uk/art/images/work/D/D20/D20910_9.jpg","max":"http://www.tate.org.uk/art/images/work/D/D20/D20910_10.jpg","page":"http://www.tate.org.uk/art/artworks/turner-landscape-gomidon-turner-d20910"},"classification":"on paper, unique","credits":"Accepted by the nation as part of the Turner Bequest 1856"},{"type":"TATE","from":"Tate Modern museum","artiste":"Joseph Mallord William Turner","artisteBio":"","date":"1828","title":"Landscape","subTitle":"","medium":"Graphite on paper","dimensions":"support: 179 x 117 mm","medias":{"mini":"http://www.tate.org.uk/art/images/work/D/D20/D20911_8.jpg","medium":"http://www.tate.org.uk/art/images/work/D/D20/D20911_9.jpg","max":"http://www.tate.org.uk/art/images/work/D/D20/D20911_10.jpg","page":"http://www.tate.org.uk/art/artworks/turner-landscape-d20911"},"classification":"on paper, unique","credits":"Accepted by the nation as part of the Turner Bequest 1856"},{"type":"TATE","from":"Tate Modern museum","artiste":"Joseph Mallord William Turner","artisteBio":"","date":"1828","title":"Stretch of Sand by River, with Tower on Hill. ?Chatel Neuve [Turner]","subTitle":"","medium":"Graphite on paper","dimensions":"support: 179 x 117 mm","medias":{"mini":"http://www.tate.org.uk/art/images/work/D/D20/D20912_8.jpg","medium":"http://www.tate.org.uk/art/images/work/D/D20/D20912_9.jpg","max":"http://www.tate.org.uk/art/images/work/D/D20/D20912_10.jpg","page":"http://www.tate.org.uk/art/artworks/turner-stretch-of-sand-by-river-with-tower-on-hill-chatel-neuve-turner-d20912"},"classification":"on paper, unique","credits":"Accepted by the nation as part of the Turner Bequest 1856"},{"type":"TATE","from":"Tate Modern museum","artiste":"Joseph Mallord William Turner","artisteBio":"","date":"1828","title":"View of Town","subTitle":"","medium":"Graphite on paper","dimensions":"support: 179 x 117 mm","medias":{"mini":"http://www.tate.org.uk/art/images/work/D/D20/D20913_8.jpg","medium":"http://www.tate.org.uk/art/images/work/D/D20/D20913_9.jpg","max":"http://www.tate.org.uk/art/images/work/D/D20/D20913_10.jpg","page":"http://www.tate.org.uk/art/artworks/turner-view-of-town-d20913"},"classification":"on paper, unique","credits":"Accepted by the nation as part of the Turner Bequest 1856"},{"type":"TATE","from":"Tate Modern museum","artiste":"Joseph Mallord William Turner","artisteBio":"","date":"1828","title":"View of Town. Riona [Turner] (near Clermont)","subTitle":"","medium":"Graphite on paper","dimensions":"support: 179 x 117 mm","medias":{"mini":"http://www.tate.org.uk/art/images/work/D/D20/D20914_8.jpg","medium":"http://www.tate.org.uk/art/images/work/D/D20/D20914_9.jpg","max":"http://www.tate.org.uk/art/images/work/D/D20/D20914_10.jpg","page":"http://www.tate.org.uk/art/artworks/turner-view-of-town-riona-turner-near-clermont-d20914"},"classification":"on paper, unique","credits":"Accepted by the nation as part of the Turner Bequest 1856"},{"type":"TATE","from":"Tate Modern museum","artiste":"Joseph Mallord William Turner","artisteBio":"","date":"1828","title":"Three Views of Town with Distant Mountains","subTitle":"","medium":"Graphite on paper","dimensions":"support: 179 x 117 mm","medias":{"mini":"http://www.tate.org.uk/art/images/work/D/D20/D20915_8.jpg","medium":"http://www.tate.org.uk/art/images/work/D/D20/D20915_9.jpg","max":"http://www.tate.org.uk/art/images/work/D/D20/D20915_10.jpg","page":"http://www.tate.org.uk/art/artworks/turner-three-views-of-town-with-distant-mountains-d20915"},"classification":"on paper, unique","credits":"Accepted by the nation as part of the Turner Bequest 1856"},{"type":"TATE","from":"Tate Modern museum","artiste":"Joseph Mallord William Turner","artisteBio":"","date":"1828","title":"Four Views of Town","subTitle":"","medium":"Graphite on paper","dimensions":"support: 179 x 117 mm","medias":{"mini":"http://www.tate.org.uk/art/images/work/D/D20/D20916_8.jpg","medium":"http://www.tate.org.uk/art/images/work/D/D20/D20916_9.jpg","max":"http://www.tate.org.uk/art/images/work/D/D20/D20916_10.jpg","page":"http://www.tate.org.uk/art/artworks/turner-four-views-of-town-d20916"},"classification":"on paper, unique","credits":"Accepted by the nation as part of the Turner Bequest 1856"},{"type":"TATE","from":"Tate Modern museum","artiste":"Joseph Mallord William Turner","artisteBio":"","date":"1828","title":"Church on Hill, with Distant Mountains","subTitle":"","medium":"Graphite on paper","dimensions":"support: 179 x 117 mm","medias":{"mini":"http://www.tate.org.uk/art/images/work/D/D20/D20917_8.jpg","medium":"http://www.tate.org.uk/art/images/work/D/D20/D20917_9.jpg","max":"http://www.tate.org.uk/art/images/work/D/D20/D20917_10.jpg","page":"http://www.tate.org.uk/art/artworks/turner-church-on-hill-with-distant-mountains-d20917"},"classification":"on paper, unique","credits":"Accepted by the nation as part of the Turner Bequest 1856"},{"type":"TATE","from":"Tate Modern museum","artiste":"Joseph Mallord William Turner","artisteBio":"","date":"1828","title":"Church on Hill, with Distant Mountains","subTitle":"","medium":"Graphite on paper","dimensions":"support: 179 x 117 mm","medias":{"mini":"http://www.tate.org.uk/art/images/work/D/D20/D20918_8.jpg","medium":"http://www.tate.org.uk/art/images/work/D/D20/D20918_9.jpg","max":"http://www.tate.org.uk/art/images/work/D/D20/D20918_10.jpg","page":"http://www.tate.org.uk/art/artworks/turner-church-on-hill-with-distant-mountains-d20918"},"classification":"on paper, unique","credits":"Accepted by the nation as part of the Turner Bequest 1856"},{"type":"TATE","from":"Tate Modern museum","artiste":"Joseph Mallord William Turner","artisteBio":"","date":"1828","title":"Church on Hill","subTitle":"","medium":"Graphite on paper","dimensions":"support: 179 x 117 mm","medias":{"mini":"http://www.tate.org.uk/art/images/work/D/D20/D20919_8.jpg","medium":"http://www.tate.org.uk/art/images/work/D/D20/D20919_9.jpg","max":"http://www.tate.org.uk/art/images/work/D/D20/D20919_10.jpg","page":"http://www.tate.org.uk/art/artworks/turner-church-on-hill-d20919"},"classification":"on paper, unique","credits":"Accepted by the nation as part of the Turner Bequest 1856"},{"type":"TATE","from":"Tate Modern museum","artiste":"Joseph Mallord William Turner","artisteBio":"","date":"1828","title":"Church on Hill","subTitle":"","medium":"Graphite on paper","dimensions":"support: 179 x 117 mm","medias":{"mini":"http://www.tate.org.uk/art/images/work/D/D20/D20920_8.jpg","medium":"http://www.tate.org.uk/art/images/work/D/D20/D20920_9.jpg","max":"http://www.tate.org.uk/art/images/work/D/D20/D20920_10.jpg","page":"http://www.tate.org.uk/art/artworks/turner-church-on-hill-d20920"},"classification":"on paper, unique","credits":"Accepted by the nation as part of the Turner Bequest 1856"},{"type":"TATE","from":"Tate Modern museum","artiste":"Joseph Mallord William Turner","artisteBio":"","date":"1828","title":"Ruins of ?Amphitheatre","subTitle":"","medium":"Graphite on paper","dimensions":"support: 179 x 117 mm","medias":{"mini":"http://www.tate.org.uk/art/images/work/D/D20/D20921_8.jpg","medium":"http://www.tate.org.uk/art/images/work/D/D20/D20921_9.jpg","max":"http://www.tate.org.uk/art/images/work/D/D20/D20921_10.jpg","page":"http://www.tate.org.uk/art/artworks/turner-ruins-of-amphitheatre-d20921"},"classification":"on paper, unique","credits":"Accepted by the nation as part of the Turner Bequest 1856"},{"type":"TATE","from":"Tate Modern museum","artiste":"Joseph Mallord William Turner","artisteBio":"","date":"1828","title":"Ruins on Hill. ?Chin [Turner]","subTitle":"","medium":"Graphite on paper","dimensions":"support: 179 x 117 mm","medias":{"mini":"http://www.tate.org.uk/art/images/work/D/D20/D20922_8.jpg","medium":"http://www.tate.org.uk/art/images/work/D/D20/D20922_9.jpg","max":"http://www.tate.org.uk/art/images/work/D/D20/D20922_10.jpg","page":"http://www.tate.org.uk/art/artworks/turner-ruins-on-hill-chin-turner-d20922"},"classification":"on paper, unique","credits":"Accepted by the nation as part of the Turner Bequest 1856"},{"type":"TATE","from":"Tate Modern museum","artiste":"Joseph Mallord William Turner","artisteBio":"","date":"1828","title":"Ruins on Hill","subTitle":"","medium":"Graphite on paper","dimensions":"support: 179 x 117 mm","medias":{"mini":"http://www.tate.org.uk/art/images/work/D/D20/D20923_8.jpg","medium":"http://www.tate.org.uk/art/images/work/D/D20/D20923_9.jpg","max":"http://www.tate.org.uk/art/images/work/D/D20/D20923_10.jpg","page":"http://www.tate.org.uk/art/artworks/turner-ruins-on-hill-d20923"},"classification":"on paper, unique","credits":"Accepted by the nation as part of the Turner Bequest 1856"},{"type":"TATE","from":"Tate Modern museum","artiste":"Joseph Mallord William Turner","artisteBio":"","date":"1828","title":"Buildings on Hill","subTitle":"","medium":"Graphite on paper","dimensions":"support: 179 x 117 mm","medias":{"mini":"http://www.tate.org.uk/art/images/work/D/D20/D20924_8.jpg","medium":"http://www.tate.org.uk/art/images/work/D/D20/D20924_9.jpg","max":"http://www.tate.org.uk/art/images/work/D/D20/D20924_10.jpg","page":"http://www.tate.org.uk/art/artworks/turner-buildings-on-hill-d20924"},"classification":"on paper, unique","credits":"Accepted by the nation as part of the Turner Bequest 1856"},{"type":"TATE","from":"Tate Modern museum","artiste":"Joseph Mallord William Turner","artisteBio":"","date":"1828","title":"Buildings on Hill","subTitle":"","medium":"Graphite on paper","dimensions":"support: 179 x 117 mm","medias":{"mini":"http://www.tate.org.uk/art/images/work/D/D20/D20925_8.jpg","medium":"http://www.tate.org.uk/art/images/work/D/D20/D20925_9.jpg","max":"http://www.tate.org.uk/art/images/work/D/D20/D20925_10.jpg","page":"http://www.tate.org.uk/art/artworks/turner-buildings-on-hill-d20925"},"classification":"on paper, unique","credits":"Accepted by the nation as part of the Turner Bequest 1856"},{"type":"TATE","from":"Tate Modern museum","artiste":"Joseph Mallord William Turner","artisteBio":"","date":"1828","title":"Buildings on Hill","subTitle":"","medium":"Graphite on paper","dimensions":"support: 179 x 117 mm","medias":{"mini":"http://www.tate.org.uk/art/images/work/D/D20/D20926_8.jpg","medium":"http://www.tate.org.uk/art/images/work/D/D20/D20926_9.jpg","max":"http://www.tate.org.uk/art/images/work/D/D20/D20926_10.jpg","page":"http://www.tate.org.uk/art/artworks/turner-buildings-on-hill-d20926"},"classification":"on paper, unique","credits":"Accepted by the nation as part of the Turner Bequest 1856"},{"type":"TATE","from":"Tate Modern museum","artiste":"Joseph Mallord William Turner","artisteBio":"","date":"1828","title":"At Avignon [Turner]","subTitle":"","medium":"Graphite on paper","dimensions":"support: 179 x 117 mm","medias":{"mini":"http://www.tate.org.uk/art/images/work/D/D20/D20927_8.jpg","medium":"http://www.tate.org.uk/art/images/work/D/D20/D20927_9.jpg","max":"http://www.tate.org.uk/art/images/work/D/D20/D20927_10.jpg","page":"http://www.tate.org.uk/art/artworks/turner-at-avignon-turner-d20927"},"classification":"on paper, unique","credits":"Accepted by the nation as part of the Turner Bequest 1856"},{"type":"TATE","from":"Tate Modern museum","artiste":"Joseph Mallord William Turner","artisteBio":"","date":"1828","title":"Bridge over the Rhône","subTitle":"","medium":"Graphite on paper","dimensions":"support: 179 x 117 mm","medias":{"mini":"http://www.tate.org.uk/art/images/work/D/D20/D20928_8.jpg","medium":"http://www.tate.org.uk/art/images/work/D/D20/D20928_9.jpg","max":"http://www.tate.org.uk/art/images/work/D/D20/D20928_10.jpg","page":"http://www.tate.org.uk/art/artworks/turner-bridge-over-the-rhone-d20928"},"classification":"on paper, unique","credits":"Accepted by the nation as part of the Turner Bequest 1856"},{"type":"TATE","from":"Tate Modern museum","artiste":"Joseph Mallord William Turner","artisteBio":"","date":"1828","title":"At Avignon [Turner]","subTitle":"","medium":"Graphite on paper","dimensions":"support: 179 x 117 mm","medias":{"mini":"http://www.tate.org.uk/art/images/work/D/D20/D20929_8.jpg","medium":"http://www.tate.org.uk/art/images/work/D/D20/D20929_9.jpg","max":"http://www.tate.org.uk/art/images/work/D/D20/D20929_10.jpg","page":"http://www.tate.org.uk/art/artworks/turner-at-avignon-turner-d20929"},"classification":"on paper, unique","credits":"Accepted by the nation as part of the Turner Bequest 1856"},{"type":"TATE","from":"Tate Modern museum","artiste":"Joseph Mallord William Turner","artisteBio":"","date":"1828","title":"Rocks, with Tower","subTitle":"","medium":"Graphite on paper","dimensions":"support: 179 x 117 mm","medias":{"mini":"http://www.tate.org.uk/art/images/work/D/D20/D20930_8.jpg","medium":"http://www.tate.org.uk/art/images/work/D/D20/D20930_9.jpg","max":"http://www.tate.org.uk/art/images/work/D/D20/D20930_10.jpg","page":"http://www.tate.org.uk/art/artworks/turner-rocks-with-tower-d20930"},"classification":"on paper, unique","credits":"Accepted by the nation as part of the Turner Bequest 1856"},{"type":"TATE","from":"Tate Modern museum","artiste":"Joseph Mallord William Turner","artisteBio":"","date":"1828","title":"Rocks, with Ruins","subTitle":"","medium":"Graphite on paper","dimensions":"support: 179 x 117 mm","medias":{"mini":"http://www.tate.org.uk/art/images/work/D/D20/D20931_8.jpg","medium":"http://www.tate.org.uk/art/images/work/D/D20/D20931_9.jpg","max":"http://www.tate.org.uk/art/images/work/D/D20/D20931_10.jpg","page":"http://www.tate.org.uk/art/artworks/turner-rocks-with-ruins-d20931"},"classification":"on paper, unique","credits":"Accepted by the nation as part of the Turner Bequest 1856"},{"type":"TATE","from":"Tate Modern museum","artiste":"Joseph Mallord William Turner","artisteBio":"","date":"1828","title":"Road over the Rocks","subTitle":"","medium":"Graphite on paper","dimensions":"support: 179 x 117 mm","medias":{"mini":"http://www.tate.org.uk/art/images/work/D/D20/D20932_8.jpg","medium":"http://www.tate.org.uk/art/images/work/D/D20/D20932_9.jpg","max":"http://www.tate.org.uk/art/images/work/D/D20/D20932_10.jpg","page":"http://www.tate.org.uk/art/artworks/turner-road-over-the-rocks-d20932"},"classification":"on paper, unique","credits":"Accepted by the nation as part of the Turner Bequest 1856"},{"type":"TATE","from":"Tate Modern museum","artiste":"Joseph Mallord William Turner","artisteBio":"","date":"1828","title":"Town on Hills","subTitle":"","medium":"Graphite on paper","dimensions":"support: 179 x 117 mm","medias":{"mini":"http://www.tate.org.uk/art/images/work/D/D20/D20933_8.jpg","medium":"http://www.tate.org.uk/art/images/work/D/D20/D20933_9.jpg","max":"http://www.tate.org.uk/art/images/work/D/D20/D20933_10.jpg","page":"http://www.tate.org.uk/art/artworks/turner-town-on-hills-d20933"},"classification":"on paper, unique","credits":"Accepted by the nation as part of the Turner Bequest 1856"},{"type":"TATE","from":"Tate Modern museum","artiste":"Joseph Mallord William Turner","artisteBio":"","date":"1828","title":"Views of Clermont and Beaucaire [Turner]","subTitle":"","medium":"Graphite on paper","dimensions":"support: 179 x 117 mm","medias":{"mini":"http://www.tate.org.uk/art/images/work/D/D20/D20934_8.jpg","medium":"http://www.tate.org.uk/art/images/work/D/D20/D20934_9.jpg","max":"http://www.tate.org.uk/art/images/work/D/D20/D20934_10.jpg","page":"http://www.tate.org.uk/art/artworks/turner-views-of-clermont-and-beaucaire-turner-d20934"},"classification":"on paper, unique","credits":"Accepted by the nation as part of the Turner Bequest 1856"},{"type":"TATE","from":"Tate Modern museum","artiste":"Joseph Mallord William Turner","artisteBio":"","date":"1828","title":"Views; One of Avig [Turner] (Avignon)","subTitle":"","medium":"Graphite on paper","dimensions":"support: 179 x 117 mm","medias":{"mini":"http://www.tate.org.uk/art/images/work/D/D20/D20935_8.jpg","medium":"http://www.tate.org.uk/art/images/work/D/D20/D20935_9.jpg","max":"http://www.tate.org.uk/art/images/work/D/D20/D20935_10.jpg","page":"http://www.tate.org.uk/art/artworks/turner-views-one-of-avig-turner-avignon-d20935"},"classification":"on paper, unique","credits":"Accepted by the nation as part of the Turner Bequest 1856"},{"type":"TATE","from":"Tate Modern museum","artiste":"Joseph Mallord William Turner","artisteBio":"","date":"1828","title":"Beaucaire [Turner]","subTitle":"","medium":"Graphite on paper","dimensions":"support: 179 x 117 mm","medias":{"mini":"http://www.tate.org.uk/art/images/work/D/D20/D20936_8.jpg","medium":"http://www.tate.org.uk/art/images/work/D/D20/D20936_9.jpg","max":"http://www.tate.org.uk/art/images/work/D/D20/D20936_10.jpg","page":"http://www.tate.org.uk/art/artworks/turner-beaucaire-turner-d20936"},"classification":"on paper, unique","credits":"Accepted by the nation as part of the Turner Bequest 1856"},{"type":"TATE","from":"Tate Modern museum","artiste":"Joseph Mallord William Turner","artisteBio":"","date":"1828","title":"Castle, and Town","subTitle":"","medium":"Graphite on paper","dimensions":"support: 179 x 117 mm","medias":{"mini":"http://www.tate.org.uk/art/images/work/D/D20/D20937_8.jpg","medium":"http://www.tate.org.uk/art/images/work/D/D20/D20937_9.jpg","max":"http://www.tate.org.uk/art/images/work/D/D20/D20937_10.jpg","page":"http://www.tate.org.uk/art/artworks/turner-castle-and-town-d20937"},"classification":"on paper, unique","credits":"Accepted by the nation as part of the Turner Bequest 1856"},{"type":"TATE","from":"Tate Modern museum","artiste":"Joseph Mallord William Turner","artisteBio":"","date":"1828","title":"Rocks","subTitle":"","medium":"Graphite on paper","dimensions":"support: 179 x 117 mm","medias":{"mini":"http://www.tate.org.uk/art/images/work/D/D20/D20938_8.jpg","medium":"http://www.tate.org.uk/art/images/work/D/D20/D20938_9.jpg","max":"http://www.tate.org.uk/art/images/work/D/D20/D20938_10.jpg","page":"http://www.tate.org.uk/art/artworks/turner-rocks-d20938"},"classification":"on paper, unique","credits":"Accepted by the nation as part of the Turner Bequest 1856"},{"type":"TATE","from":"Tate Modern museum","artiste":"Joseph Mallord William Turner","artisteBio":"","date":"1828","title":"River Scene, with Bridge, and Figures Taking out Sand [Turner] from Boat","subTitle":"","medium":"Graphite on paper","dimensions":"support: 179 x 117 mm","medias":{"mini":"http://www.tate.org.uk/art/images/work/D/D20/D20939_8.jpg","medium":"http://www.tate.org.uk/art/images/work/D/D20/D20939_9.jpg","max":"http://www.tate.org.uk/art/images/work/D/D20/D20939_10.jpg","page":"http://www.tate.org.uk/art/artworks/turner-river-scene-with-bridge-and-figures-taking-out-sand-turner-from-boat-d20939"},"classification":"on paper, unique","credits":"Accepted by the nation as part of the Turner Bequest 1856"},{"type":"TATE","from":"Tate Modern museum","artiste":"Joseph Mallord William Turner","artisteBio":"","date":"1828","title":"A Castle. ?C. Lemair [Turner]","subTitle":"","medium":"Graphite on paper","dimensions":"support: 179 x 117 mm","medias":{"mini":"http://www.tate.org.uk/art/images/work/D/D20/D20940_8.jpg","medium":"http://www.tate.org.uk/art/images/work/D/D20/D20940_9.jpg","max":"http://www.tate.org.uk/art/images/work/D/D20/D20940_10.jpg","page":"http://www.tate.org.uk/art/artworks/turner-a-castle-c-lemair-turner-d20940"},"classification":"on paper, unique","credits":"Accepted by the nation as part of the Turner Bequest 1856"},{"type":"TATE","from":"Tate Modern museum","artiste":"Joseph Mallord William Turner","artisteBio":"","date":"1828","title":"Landscape. ?Dunn [Turner]","subTitle":"","medium":"Graphite on paper","dimensions":"support: 179 x 117 mm","medias":{"mini":"http://www.tate.org.uk/art/images/work/D/D20/D20941_8.jpg","medium":"http://www.tate.org.uk/art/images/work/D/D20/D20941_9.jpg","max":"http://www.tate.org.uk/art/images/work/D/D20/D20941_10.jpg","page":"http://www.tate.org.uk/art/artworks/turner-landscape-dunn-turner-d20941"},"classification":"on paper, unique","credits":"Accepted by the nation as part of the Turner Bequest 1856"},{"type":"TATE","from":"Tate Modern museum","artiste":"Joseph Mallord William Turner","artisteBio":"","date":"1828","title":"Views at Avignon, Arles [Turner], Etc.","subTitle":"","medium":"Graphite on paper","dimensions":"support: 179 x 117 mm","medias":{"mini":"http://www.tate.org.uk/art/images/work/D/D20/D20942_8.jpg","medium":"http://www.tate.org.uk/art/images/work/D/D20/D20942_9.jpg","max":"http://www.tate.org.uk/art/images/work/D/D20/D20942_10.jpg","page":"http://www.tate.org.uk/art/artworks/turner-views-at-avignon-arles-turner-etc-d20942"},"classification":"on paper, unique","credits":"Accepted by the nation as part of the Turner Bequest 1856"},{"type":"TATE","from":"Tate Modern museum","artiste":"Joseph Mallord William Turner","artisteBio":"","date":"1828","title":"Walls of a City. W. of Ly. [Turner] (?Lyons)","subTitle":"","medium":"Graphite on paper","dimensions":"support: 179 x 117 mm","medias":{"mini":"http://www.tate.org.uk/art/images/work/D/D20/D20943_8.jpg","medium":"http://www.tate.org.uk/art/images/work/D/D20/D20943_9.jpg","max":"http://www.tate.org.uk/art/images/work/D/D20/D20943_10.jpg","page":"http://www.tate.org.uk/art/artworks/turner-walls-of-a-city-w-of-ly-turner-lyons-d20943"},"classification":"on paper, unique","credits":"Accepted by the nation as part of the Turner Bequest 1856"},{"type":"TATE","from":"Tate Modern museum","artiste":"Joseph Mallord William Turner","artisteBio":"","date":"1828","title":"Town on Hill","subTitle":"","medium":"Graphite on paper","dimensions":"support: 179 x 117 mm","medias":{"mini":"http://www.tate.org.uk/art/images/work/D/D20/D20944_8.jpg","medium":"http://www.tate.org.uk/art/images/work/D/D20/D20944_9.jpg","max":"http://www.tate.org.uk/art/images/work/D/D20/D20944_10.jpg","page":"http://www.tate.org.uk/art/artworks/turner-town-on-hill-d20944"},"classification":"on paper, unique","credits":"Accepted by the nation as part of the Turner Bequest 1856"},{"type":"TATE","from":"Tate Modern museum","artiste":"Joseph Mallord William Turner","artisteBio":"","date":"1828","title":"Castle on Hill, Etc.","subTitle":"","medium":"Graphite on paper","dimensions":"support: 179 x 117 mm","medias":{"mini":"http://www.tate.org.uk/art/images/work/D/D20/D20945_8.jpg","medium":"http://www.tate.org.uk/art/images/work/D/D20/D20945_9.jpg","max":"http://www.tate.org.uk/art/images/work/D/D20/D20945_10.jpg","page":"http://www.tate.org.uk/art/artworks/turner-castle-on-hill-etc-d20945"},"classification":"on paper, unique","credits":"Accepted by the nation as part of the Turner Bequest 1856"},{"type":"TATE","from":"Tate Modern museum","artiste":"Joseph Mallord William Turner","artisteBio":"","date":"1828","title":"Castle on Hill, Etc.","subTitle":"","medium":"Graphite on paper","dimensions":"support: 179 x 117 mm","medias":{"mini":"http://www.tate.org.uk/art/images/work/D/D20/D20946_8.jpg","medium":"http://www.tate.org.uk/art/images/work/D/D20/D20946_9.jpg","max":"http://www.tate.org.uk/art/images/work/D/D20/D20946_10.jpg","page":"http://www.tate.org.uk/art/artworks/turner-castle-on-hill-etc-d20946"},"classification":"on paper, unique","credits":"Accepted by the nation as part of the Turner Bequest 1856"},{"type":"TATE","from":"Tate Modern museum","artiste":"Joseph Mallord William Turner","artisteBio":"","date":"1828","title":"Castle on Hill, Etc.","subTitle":"","medium":"Graphite on paper","dimensions":"support: 179 x 117 mm","medias":{"mini":"http://www.tate.org.uk/art/images/work/D/D20/D20947_8.jpg","medium":"http://www.tate.org.uk/art/images/work/D/D20/D20947_9.jpg","max":"http://www.tate.org.uk/art/images/work/D/D20/D20947_10.jpg","page":"http://www.tate.org.uk/art/artworks/turner-castle-on-hill-etc-d20947"},"classification":"on paper, unique","credits":"Accepted by the nation as part of the Turner Bequest 1856"},{"type":"TATE","from":"Tate Modern museum","artiste":"Joseph Mallord William Turner","artisteBio":"","date":"1828","title":"Castle on Hill, Etc.","subTitle":"","medium":"Graphite on paper","dimensions":"support: 179 x 117 mm","medias":{"mini":"http://www.tate.org.uk/art/images/work/D/D20/D20948_8.jpg","medium":"http://www.tate.org.uk/art/images/work/D/D20/D20948_9.jpg","max":"http://www.tate.org.uk/art/images/work/D/D20/D20948_10.jpg","page":"http://www.tate.org.uk/art/artworks/turner-castle-on-hill-etc-d20948"},"classification":"on paper, unique","credits":"Accepted by the nation as part of the Turner Bequest 1856"},{"type":"TATE","from":"Tate Modern museum","artiste":"Joseph Mallord William Turner","artisteBio":"","date":"1828","title":"Castle on Hill, Etc.","subTitle":"","medium":"Graphite on paper","dimensions":"support: 179 x 117 mm","medias":{"mini":"http://www.tate.org.uk/art/images/work/D/D20/D20949_8.jpg","medium":"http://www.tate.org.uk/art/images/work/D/D20/D20949_9.jpg","max":"http://www.tate.org.uk/art/images/work/D/D20/D20949_10.jpg","page":"http://www.tate.org.uk/art/artworks/turner-castle-on-hill-etc-d20949"},"classification":"on paper, unique","credits":"Accepted by the nation as part of the Turner Bequest 1856"},{"type":"TATE","from":"Tate Modern museum","artiste":"Joseph Mallord William Turner","artisteBio":"","date":"1828","title":"Castle on Hill, Etc. Sciria [Turner] (?Sarras, on the Rhine, or La Séreyrède, near Lyons)","subTitle":"","medium":"Graphite on paper","dimensions":"support: 179 x 117 mm","medias":{"mini":"http://www.tate.org.uk/art/images/work/D/D20/D20950_8.jpg","medium":"http://www.tate.org.uk/art/images/work/D/D20/D20950_9.jpg","max":"http://www.tate.org.uk/art/images/work/D/D20/D20950_10.jpg","page":"http://www.tate.org.uk/art/artworks/turner-castle-on-hill-etc-sciria-turner-sarras-on-the-rhine-or-la-sereyrede-near-lyons-d20950"},"classification":"on paper, unique","credits":"Accepted by the nation as part of the Turner Bequest 1856"},{"type":"TATE","from":"Tate Modern museum","artiste":"Joseph Mallord William Turner","artisteBio":"","date":"1828","title":"Castle on Hill, Etc. S. Vivier [Turner] (?Viviers-sur-Rhône)","subTitle":"","medium":"Graphite on paper","dimensions":"support: 179 x 117 mm","medias":{"mini":"http://www.tate.org.uk/art/images/work/D/D20/D20951_8.jpg","medium":"http://www.tate.org.uk/art/images/work/D/D20/D20951_9.jpg","max":"http://www.tate.org.uk/art/images/work/D/D20/D20951_10.jpg","page":"http://www.tate.org.uk/art/artworks/turner-castle-on-hill-etc-s-vivier-turner-viviers-sur-rhone-d20951"},"classification":"on paper, unique","credits":"Accepted by the nation as part of the Turner Bequest 1856"}]